adams/__init__.py
adams/_version.py
adams/adams_zero.py
adams/py.typed
adams_torch-0.0.1.dist-info/licenses/LICENSE
adams_torch-0.0.1.dist-info/METADATA
adams_torch-0.0.1.dist-info/WHEEL
adams_torch-0.0.1.dist-info/top_level.txt
adams_torch-0.0.1.dist-info/RECORD
