Metadata-Version: 2.4
Name: adams-torch
Version: 0.0.1
Summary: Adams optimizer: next-generation optimizer blending element-wise methods with matrix-aware regularization
Author: One
License-Expression: Apache-2.0
Project-URL: Homepage, https://github.com/imoneoi/Adams
Project-URL: Repository, https://github.com/imoneoi/Adams
Project-URL: Issues, https://github.com/imoneoi/Adams/issues
Keywords: pytorch,optimizer,deep learning,machine learning,spectral regularization
Classifier: Development Status :: 4 - Beta
Classifier: Intended Audience :: Developers
Classifier: Intended Audience :: Science/Research
Classifier: Operating System :: OS Independent
Classifier: Programming Language :: Python :: 3
Classifier: Programming Language :: Python :: 3.8
Classifier: Programming Language :: Python :: 3.9
Classifier: Programming Language :: Python :: 3.10
Classifier: Programming Language :: Python :: 3.11
Classifier: Programming Language :: Python :: 3.12
Classifier: Topic :: Scientific/Engineering :: Artificial Intelligence
Classifier: Topic :: Software Development :: Libraries :: Python Modules
Requires-Python: >=3.8
License-File: LICENSE
Requires-Dist: torch>=1.12.0
Dynamic: license-file
